nb_metadata_handler/__init__.py
nb_metadata_handler/_version.py
nb_metadata_handler-0.2.0.data/data/share/jupyter/labextensions/nb-metadata-handler/package.json
nb_metadata_handler-0.2.0.data/data/share/jupyter/labextensions/nb-metadata-handler/schemas/nb-metadata-handler/package.json.orig
nb_metadata_handler-0.2.0.data/data/share/jupyter/labextensions/nb-metadata-handler/schemas/nb-metadata-handler/plugin.json
nb_metadata_handler-0.2.0.data/data/share/jupyter/labextensions/nb-metadata-handler/static/656.0789ef775163fa367785.js
nb_metadata_handler-0.2.0.data/data/share/jupyter/labextensions/nb-metadata-handler/static/728.2cf90ef7bf9bfb3451ff.js
nb_metadata_handler-0.2.0.data/data/share/jupyter/labextensions/nb-metadata-handler/static/remoteEntry.7d6f4d86ac84d22dae03.js
nb_metadata_handler-0.2.0.data/data/share/jupyter/labextensions/nb-metadata-handler/static/style.js
nb_metadata_handler-0.2.0.data/data/share/jupyter/labextensions/nb-metadata-handler/static/third-party-licenses.json
nb_metadata_handler-0.2.0.data/data/share/jupyter/labextensions/nb-metadata-handler/install.json
nb_metadata_handler-0.2.0.dist-info/METADATA
nb_metadata_handler-0.2.0.dist-info/WHEEL
nb_metadata_handler-0.2.0.dist-info/licenses/LICENSE
nb_metadata_handler-0.2.0.dist-info/RECORD
