Metadata-Version: 2.4
Name: nb_metadata_handler
Version: 0.2.0
Summary: A JupyterLab extension to handle notebook metadata.
Project-URL: Homepage, https://github.com/brichet/nb-metadata-handler
Project-URL: Bug Tracker, https://github.com/brichet/nb-metadata-handler/issues
Project-URL: Repository, https://github.com/brichet/nb-metadata-handler.git
Author: Nicolas Brichet
License: BSD 3-Clause License
License-File: LICENSE
Keywords: jupyter,jupyterlab,jupyterlab-extension
Classifier: Framework :: Jupyter
Classifier: Framework :: Jupyter :: JupyterLab
Classifier: Framework :: Jupyter :: JupyterLab :: 4
Classifier: Framework :: Jupyter :: JupyterLab :: Extensions
Classifier: Framework :: Jupyter :: JupyterLab :: Extensions :: Prebuilt
Classifier: License :: OSI Approved :: BSD License
Classifier: Programming Language :: Python
Classifier: Programming Language :: Python :: 3
Classifier: Programming Language :: Python :: 3.9
Classifier: Programming Language :: Python :: 3.10
Classifier: Programming Language :: Python :: 3.11
Classifier: Programming Language :: Python :: 3.12
Classifier: Programming Language :: Python :: 3.13
Requires-Python: >=3.9
